mkdocs_i18n/__init__.py
mkdocs_i18n-0.4.6.dist-info/COPYING
mkdocs_i18n-0.4.6.dist-info/METADATA
mkdocs_i18n-0.4.6.dist-info/WHEEL
mkdocs_i18n-0.4.6.dist-info/entry_points.txt
mkdocs_i18n-0.4.6.dist-info/top_level.txt
mkdocs_i18n-0.4.6.dist-info/RECORD
