Metadata-Version: 2.1
Name: mkdocs-i18n
Version: 0.4.6
Summary: MkDocs i18n plugin
Author-email: Simó Albert i Beltran <sim6@bona.gent>
License: AGPL-3.0-or-later
Project-URL: Homepage, https://gitlab.com/mkdocs-i18n/mkdocs-i18n
Project-URL: Bug Reports, https://gitlab.com/mkdocs-i18n/mkdocs-i18n/-/issues
Project-URL: Funding, https://liberapay.com/mkdocs-i18n/donate
Project-URL: Source, https://gitlab.com/mkdocs-i18n/mkdocs-i18n/-/tree/main
Keywords: mkdocs,plugin,i18n
Classifier: Development Status :: 5 - Production/Stable
Classifier: License :: OSI Approved :: GNU Affero General Public License v3 or later (AGPLv3+)
Classifier: Programming Language :: Python
Classifier: Programming Language :: Python :: 3 :: Only
Classifier: Programming Language :: Python :: 3.7
Classifier: Programming Language :: Python :: 3.9
Requires-Python: <4,>=3.7
Provides-Extra: test
License-File: COPYING
